narator/__init__.py
narator/narator
narator/templates/template.txt
narator-0.1.1.data/scripts/narator
narator-0.1.1.dist-info/LICENSE
narator-0.1.1.dist-info/METADATA
narator-0.1.1.dist-info/WHEEL
narator-0.1.1.dist-info/top_level.txt
narator-0.1.1.dist-info/RECORD
