Metadata-Version: 2.1
Name: narator
Version: 0.1.1
Summary: Generate markdown work-reports from the body of github issues.
Home-page: UNKNOWN
Author: Mihai Dincă
Author-email: dincamihai@gmail.com
License: MIT
Platform: UNKNOWN
Requires-Dist: jinja2
Requires-Dist: requests
